README.txt
setup.py
CombatWiz.egg-info/PKG-INFO
CombatWiz.egg-info/SOURCES.txt
CombatWiz.egg-info/dependency_links.txt
CombatWiz.egg-info/requires.txt
CombatWiz.egg-info/top_level.txt
combatwiz/__init__.py
combatwiz/randomizer.py
scripts/combatwiz_runner.py