Metadata-Version: 1.1
Name: CombatWiz
Version: 0.11
Summary: A combat simulator
Home-page: http://github.com/kenfar/CombatSim
Author: Ben Farmer, Ken Farmer
Author-email: kenfar@gmail.com
License: BSD
Download-URL: http://github.com/downloads/kenfar/CombatWiz/CombatWiz-0.11.tar.gz
Platform: UNKNOWN
Classifier: Development Status :: 3 - Alpha
Classifier: Environment :: Console
Classifier: License :: OSI Approved :: BSD License
Classifier: Programming Language :: Python
Classifier: Operating System :: POSIX
Classifier: Topic :: Games/Entertainment :: Role-Playing
Classifier: Topic :: Games/Entertainment :: Simulation
